cicsim/__init__.py
cicsim/cdsconf.py
cicsim/cicsim.py
cicsim/cmdarchive.py
cicsim/cmdip.py
cicsim/cmdresults.py
cicsim/cmdrun.py
cicsim/cmdrunng.py
cicsim/cmdsimdir.py
cicsim/cmdsimdirng.py
cicsim/cmdspider.py
cicsim/cmdsummary.py
cicsim/cmdwave.py
cicsim/command.py
cicsim/ngraw.py
cicsim/plot.py
cicsim/simcalc.py
cicsim/spec.py
cicsim/spiceparser.py
cicsim/wavebrowser.py
cicsim/wavefiles.py
cicsim/wavegraph.py
cicsim-0.1.17.dist-info/licenses/LICENSE
cicsim-0.1.17.dist-info/METADATA
cicsim-0.1.17.dist-info/WHEEL
cicsim-0.1.17.dist-info/entry_points.txt
cicsim-0.1.17.dist-info/top_level.txt
cicsim-0.1.17.dist-info/RECORD
