Metadata-Version: 2.4
Name: cicsim
Version: 0.1.17
Summary: Custom IC Creator Simulation Tools
Home-page: https://github.com/wulffern/cicsim
Author: Carsten Wulff
Author-email: Carsten Wulff <carsten@wulff.no>
License-Expression: MIT
Project-URL: Homepage, https://github.com/wulffern/cicsim
Project-URL: Bug Tracker, https://github.com/wulffern/cicsim/issues
Classifier: Programming Language :: Python :: 3
Classifier: Operating System :: OS Independent
Requires-Python: >=3.8
License-File: LICENSE
Requires-Dist: numpy
Requires-Dist: pandas
Requires-Dist: jinja2
Requires-Dist: matplotlib
Dynamic: author
Dynamic: home-page
Dynamic: license-file
Dynamic: requires-python
